langchain_xiao/__init__.py
langchain_xiao/chat_models/__init__.py
langchain_xiao/chat_models/baichuan.py
langchain_xiao/chat_models/cyou.py
langchain_xiao/chat_models/hunyuan.py
langchain_xiao/chat_models/llamacpp.py
langchain_xiao/chat_models/tongyi.py
langchain_xiao/chat_models/utils.py
langchain_xiao/embeddings/__init__.py
langchain_xiao/embeddings/fastllm.py
langchain_xiao/embeddings/xinference.py
langchain_xiao/llms/__init__.py
langchain_xiao/llms/gpt4all.py
langchain_xiao/llms/utils.py
langchain_xiao/retrievers/__init__.py
langchain_xiao/retrievers/document_compressors/__init__.py
langchain_xiao/retrievers/document_compressors/fastllm_rerank.py
langchain_xiao/retrievers/document_compressors/xinference_rerank.py
langchain_xiao-0.0.9.dist-info/LICENSE
langchain_xiao-0.0.9.dist-info/METADATA
langchain_xiao-0.0.9.dist-info/WHEEL
langchain_xiao-0.0.9.dist-info/top_level.txt
langchain_xiao-0.0.9.dist-info/RECORD
